ling2me
