Metadata-Version: 2.1
Name: ling2me
Version: 0.0.10
Summary: A Python module to translate
Home-page: https://github.com/nicolasmarin/ling2me-python
Author: nicolasmarin
Author-email: info@ling2me.com
License: GPLv3
Download-URL: https://github.com/nicolasmarin/ling2me-python/archive/refs/heads/main.zip
Keywords: api translate,translate,languages, translated,translating
Platform: UNKNOWN
Classifier: Programming Language :: Python :: 3
Classifier: Operating System :: OS Independent
Classifier: Topic :: Software Development :: Build Tools
Classifier: License :: OSI Approved :: GNU General Public License v3 (GPLv3)
